trafficLight.v
module trafficLight(clock,reset, gLength, yLength, rLength, carCount, light,walkButton, walkLight, walkCount);
    input clock;
    input reset; 
    input walkButton;
    input [10:0] gLength; //length of green light
    input [10:0] yLength; //length of yellow light
    input [10:0] rLength; //length of red light
    output [8:0] carCount; //total cars passed in sequence
    output [1:0] light; //current light color 
    output [8:0] walkCount; //count of "people" walked during a red light
    output walkLight; //use to "display" walk light
    reg [8:0] carCount; 
    reg [8:0] walkCount;
    reg [1:0] light;
    reg walkLight; 
    

    reg [10:0] currentCounterGreen; //store the time left on green light
    reg [10:0] currentCounterYellow; //store the time left on yellow light
    reg [10:0] currentCounterRed; //store the time left on red light
    //yellow light helper
    reg yellowFlipper = 0; //May not technically be accurate but idea is less cars go through yellow light so every other posEdge send a car through...
    reg walkEnable = 0; 
    
    //light options 
    //00: red
    //01: yellow
    //11: green
    
    always @(posedge clock) begin 
        if(reset) begin
            currentCounterGreen <= 0;
            currentCounterYellow <= 0;
            currentCounterRed <= 0;
            light <= 2'b00;
            carCount <= 0;
            walkCount <= 0;
            walkEnable <= 0;
            walkLight <= 0;
            yellowFlipper <= 0;
        end
        else begin
            if(light == 2'b00 && currentCounterGreen == 0 && currentCounterYellow == 0 && currentCounterRed == 0 )begin //right after a reset
                currentCounterGreen <= gLength;
                currentCounterYellow <= yLength;
                currentCounterRed <= rLength;
                walkEnable <= 0;
                light <= 2'b10;
                walkLight <= 0;
            end
            if(walkButton && (light == 2'b01 || light == 2'b11))begin //button was pushed during green or yellow cycle so 
                walkEnable <= walkButton;
            end
            if(light == 2'b10) begin //we are at a green light so count passing cars and 
                carCount <= carCount + 1;
                currentCounterGreen <= currentCounterGreen - 1;
                if(currentCounterGreen == 0) begin //the green light period is now over so set light to yellow
                    light <= 2'b01;
                    yellowFlipper = 0;
                end
            end
            else if(light == 2'b01)begin // cars pass by at "half" speed
                if(yellowFlipper)begin
                    carCount <= carCount + 1;
                    currentCounterYellow <= currentCounterYellow - 1;
                    yellowFlipper <= 0;
                    if(currentCounterYellow == 0)begin
                        light <= 2'b00; //yellow period is over so set light to red
                    end
                end
                else begin //flipper is off so reduce light cycle time but do not increase count;
                    yellowFlipper <= 1; 
                    currentCounterYellow <= currentCounterYellow - 1;
                    if(currentCounterYellow == 0)begin
                        light <= 2'b00; //yellow period is over so set light to red
                    end
                    
                end
            end
            else begin //light == 2'b00 so its red but we need to check if the walkButton was pressed during green or yellow cycle
                if(currentCounterRed != 0)begin
                    if (walkEnable) begin
                        walkLight <= 1;
                        walkCount <= walkCount + 1; 
                    end
                    currentCounterRed <= currentCounterRed - 1;
                end
            end
        end    
        
    end
endmodule

clock.v
module clock (
    output clock
);
    reg clock = 1;

    initial begin
        forever begin
            #10 clock = !clock;
        end
    end

endmodule

trafficLight_tb.v
`timescale 1ns / 1ns
`include "trafficLight.v"
`include "clock.v"

module trafficLight_tb;
    wire importClock;
    reg clock;
    reg reset; 
    reg walkButton;
    reg [10:0] gLength, yLength, rLength;
    wire [8:0] count;
    wire [1:0] lightType;  
    wire [8:0] walkCount;
    wire walkLight;
    clock CLK(importClock); 
    trafficLight UTT(clock, reset, gLength, yLength, rLength, count, lightType, walkButton, walkLight, walkCount);

    //loop variable for displaying traffic light states
    integer i;

    //clock to drive traffic light
    initial begin
        forever begin
            clock = importClock;
            #10;
            clock = importClock;
        end
    end

    initial begin
        $dumpfile("trafficLight_tb.vcd");
        $dumpvars(0, trafficLight_tb);
        reset = 1; //initalize all variables
        #10;
        //set inputs and turn off reset to run
        gLength = 10'b0000001000; 
        yLength = 10'b0000000010;
        rLength = 10'b0000001000;
        walkButton = 0;
        reset = 0;
        #10;
        
        for (i = gLength + yLength + rLength; i > 0; i = i - 1) begin
            case (lightType)
                0:begin
                    $display("RED light with car count %b", count);
                    #20;
                    if (walkLight) begin
                        $display("Walk light is ON with people count: %b", walkCount);
                        #20;
                    end
                    else begin
                        $display("Walk light is OFF with people count: %b", walkCount);
                        #20;
                    end
                end 
                1:begin
                    walkButton = 1; //someone clicked the walk button when the light turned yellow
                    $display("YELLOW light with total car count %b", count);
                    #20;
                    if(walkButton)begin
                        $display("Walk button has been clicked",);
                    end
                end 
                2:begin
                    $display("GREEN light with total car count %b", count);
                    #20;
                    if(walkButton)begin
                        $display("Walk button has been clicked",);
                    end
                end 
            endcase
        end

        $finish;
        
    end
endmodule

trafficLight_tb.vcd
$date
	Sun Mar 13 20:21:21 2022
$end
$version
	Icarus Verilog
$end
$timescale
	1ns
$end
$scope module trafficLight_tb $end
$var wire 1 ! walkLight $end
$var wire 9 " walkCount [8:0] $end
$var wire 2 # lightType [1:0] $end
$var wire 1 $ importClock $end
$var wire 9 % count [8:0] $end
$var reg 1 & clock $end
$var reg 11 ' gLength [10:0] $end
$var reg 11 ( rLength [10:0] $end
$var reg 1 ) reset $end
$var reg 1 * walkButton $end
$var reg 11 + yLength [10:0] $end
$var integer 32 , i [31:0] $end
$scope module CLK $end
$var reg 1 $ clock $end
$upscope $end
$scope module UTT $end
$var wire 1 & clock $end
$var wire 11 - gLength [10:0] $end
$var wire 11 . rLength [10:0] $end
$var wire 1 ) reset $end
$var wire 1 * walkButton $end
$var wire 11 / yLength [10:0] $end
$var reg 9 0 carCount [8:0] $end
$var reg 11 1 currentCounterGreen [10:0] $end
$var reg 11 2 currentCounterRed [10:0] $end
$var reg 11 3 currentCounterYellow [10:0] $end
$var reg 2 4 light [1:0] $end
$var reg 9 5 walkCount [8:0] $end
$var reg 1 6 walkEnable $end
$var reg 1 ! walkLight $end
$var reg 1 7 yellowFlipper $end
$upscope $end
$upscope $end
$enddefinitions $end
#0
$dumpvars
07
06
b0 5
b0 4
b0 3
b0 2
b0 1
b0 0
bx /
bx .
bx -
bx ,
bx +
x*
1)
bx (
bx '
1&
b0 %
1$
b0 #
b0 "
0!
$end
#10
0)
0*
b1000 (
b1000 .
b10 +
b10 /
b1000 '
b1000 -
0&
0$
#20
b10 #
b10 4
b1000 2
b10 3
b1000 1
b10010 ,
1&
1$
#30
0&
0$
#40
b111 1
b1 %
b1 0
1&
1$
#50
0&
0$
#60
b110 1
b10 %
b10 0
1&
1$
b10001 ,
#70
0&
0$
#80
b101 1
b11 %
b11 0
1&
1$
b10000 ,
#90
0&
0$
#100
b100 1
b100 %
b100 0
1&
1$
b1111 ,
#110
0&
0$
#120
b11 1
b101 %
b101 0
1&
1$
b1110 ,
#130
0&
0$
#140
b10 1
b110 %
b110 0
1&
1$
b1101 ,
#150
0&
0$
#160
b1 1
b111 %
b111 0
1&
1$
b1100 ,
#170
0&
0$
#180
b0 1
b1000 %
b1000 0
1&
1$
b1011 ,
#190
0&
0$
#200
b1 #
b1 4
b11111111111 1
b1001 %
b1001 0
1&
1$
b1010 ,
#210
0&
0$
#220
b1 3
17
16
1&
1$
1*
b1001 ,
#230
0&
0$
#240
07
b0 3
b1010 %
b1010 0
1&
1$
b1000 ,
#250
0&
0$
#260
b0 #
b0 4
b11111111111 3
17
1&
1$
b111 ,
#270
0&
0$
#280
b111 2
b1 "
b1 5
1!
1&
1$
b110 ,
#290
0&
0$
#300
b110 2
b10 "
b10 5
1&
1$
#310
0&
0$
#320
b101 2
b11 "
b11 5
1&
1$
b101 ,
#330
0&
0$
#340
b100 2
b100 "
b100 5
1&
1$
#350
0&
0$
#360
b11 2
b101 "
b101 5
1&
1$
b100 ,
#370
0&
0$
#380
b10 2
b110 "
b110 5
1&
1$
#390
0&
0$
#400
b1 2
b111 "
b111 5
1&
1$
b11 ,
#410
0&
0$
#420
b0 2
b1000 "
b1000 5
1&
1$
#430
0&
0$
#440
1&
1$
b10 ,
#450
0&
0$
#460
1&
1$
#470
0&
0$
#480
1&
1$
b1 ,
#490
0&
0$
#500
1&
1$
#510
0&
0$
#520
1&
1$
b0 ,
